{
  "name": "capstone.malcolm.hale",
  "description": "Data Science CoLab Capstone project",
  "status": "Development",
  "permissions": {
    "usageType": "openSource",
    "licenses": [
      {
        "URL": "https://api.github.com/licenses/unlicense",
        "name": "The Unlicense"
      }
    ]
  },
  "organization": "Department of Health and Human Services",
  "homepageURL": "https://github.com/HHS/capstone.malcolm.hale",
  "downloadURL": "https://api.github.com/repos/HHS/capstone.malcolm.hale/downloads",
  "repositoryURL": "https://github.com/HHS/capstone.malcolm.hale.git",
  "vcs": "git",
  "laborHours": 0.0,
  "languages": [
    "R"
  ],
  "date": {
    "created": "2018-05-15",
    "lastModified": "2018-06-28",
    "metadataLastUpdated": "2022-03-22"
  },
  "tags": [
    "Science",
    "CoLab",
    "Capstone",
    "project"
  ],
  "contact": {
    "email": "HHS_GitHub_Service_Desk@hhs.gov",
    "name": "U.S. Department of Health & Human Services"
  }
}
