{
  "name": "Tableau-Dashboards",
  "description": "Tableau Dashboards",
  "status": "Development",
  "permissions": {
    "usageType": "openSource",
    "licenses": null
  },
  "organization": "Department of Health and Human Services",
  "homepageURL": "https://github.com/HHS/Tableau-Dashboards",
  "downloadURL": "https://api.github.com/repos/HHS/Tableau-Dashboards/downloads",
  "repositoryURL": "https://github.com/HHS/Tableau-Dashboards.git",
  "vcs": "git",
  "laborHours": 0.0,
  "languages": [],
  "date": {
    "created": "2021-08-10",
    "lastModified": "2021-08-10",
    "metadataLastUpdated": "2022-03-22"
  },
  "tags": [
    "Tableau",
    "Dashboards"
  ],
  "contact": {
    "email": "HHS_GitHub_Service_Desk@hhs.gov",
    "name": "U.S. Department of Health & Human Services"
  }
}
