{
  "name": "hig-devops",
  "description": "hig-devops",
  "status": "Development",
  "permissions": {
    "usageType": "openSource",
    "licenses": null
  },
  "organization": "Department of Health and Human Services",
  "homepageURL": "https://github.com/HHS/hig-devops",
  "downloadURL": "https://api.github.com/repos/HHS/hig-devops/downloads",
  "repositoryURL": "https://github.com/HHS/hig-devops.git",
  "vcs": "git",
  "laborHours": 0.0,
  "languages": [
    "HCL",
    "Shell"
  ],
  "date": {
    "created": "2021-10-12",
    "lastModified": "2022-02-14",
    "metadataLastUpdated": "2022-03-22"
  },
  "tags": [
    "hig",
    "devops"
  ],
  "contact": {
    "email": "HHS_GitHub_Service_Desk@hhs.gov",
    "name": "U.S. Department of Health & Human Services"
  }
}
